Workbook
Name Slicer_product_category: #N/A
Name Slicer_product_type: #N/A
Name Slicer_store_id: #N/A
Name Slicer_store_location: #N/A
Name Slicer_transaction_id: #N/A

Sheet Cover
A1: Bright Coffee Shop Sales — CEO Presentation
A2: Actionable insights from 1 000 transactions covering product revenue, daypart performance, trends, and CEO recommendations.
A4: CONTENTS | B4: WHAT TO USE IT FOR
A5: CEO Dashboard | B5: Headline KPIs, product/category performance, daypart trends, and store comparison.
A6: Product Insights | B6: Detailed product-category and product-type revenue tables with ranked charts.
A7: Time Insights | B7: Hour, time-of-day, daily, and weekday/weekend performance analysis.
A8: Recommendations | B8: Prioritized and expanded recommendations for improving sales performance.
A9: Bright Coffee Shop dataset | B9: Source transaction table used by all formulas and charts.
A10: Products Dashboard | B10: Objective dashboard for highest-revenue products and categories.
A11: Daypart Dashboard | B11: Objective dashboard for best-performing time of day and hourly performance.
A12: Sales Trends Dashboard | B12: Objective dashboard for product revenue across time intervals.
A13: Action Dashboard | B13: CEO action plan plus expanded sales performance recommendations.

Sheet Category Pivots
A3: Row Labels | B3: Count of revenue | H3: Row Labels | I3: Count of revenue
A4: Bakery | B4: 132 | H4: Barista Espresso | I4: 115
A5: Coffee | B5: 444 | H5: Biscotti | I5: 32
A6: Drinking Chocolate | B6: 80 | H6: Brewed Black tea | I6: 78
A7: Tea | B7: 344 | H7: Brewed Chai tea | I7: 134
A8: Grand Total | B8: 1000 | H8: Brewed Green tea | I8: 48
H9: Brewed herbal tea | I9: 84
H10: Drip coffee | I10: 76
A11: Row Labels | B11: Count of revenue | H11: Gourmet brewed coffee | I11: 116
A12: Astoria | B12: 337 | H12: Hot chocolate | I12: 80
A13: Hell's Kitchen | B13: 339 | H13: Organic brewed coffee | I13: 74
A14: Lower Manhattan | B14: 324 | H14: Pastry | I14: 37
A15: Grand Total | B15: 1000 | H15: Premium brewed coffee | I15: 63
H16: Scone | I16: 63
H17: Grand Total | I17: 1000
A21: Row Labels | B21: Count of revenue
A22: Bakery | B22: 132
A23: Coffee | B23: 444
A24: Drinking Chocolate | B24: 80
A25: Tea | B25: 344
A26: Grand Total | B26: 1000
A32: Row Labels | B32: Count of product_id
A33: Bakery | B33: 132
A34: Coffee | B34: 444
A35: Drinking Chocolate | B35: 80
A36: Tea | B36: 344
A37: Grand Total | B37: 1000

Sheet Price Hour Pivots
A3: Row Labels | B3: Sum of hour
A4: 2 | B4: 304
A5: 2.2 | B5: 187 | L5: Row Labels | M5: Count of transaction_qty
A6: 2.45 | B6: 94 | L6: 2 | M6: 23 | N6: Row Labels | O6: Count of transaction_qty
A7: 2.5 | B7: 1400 | L7: 2.2 | M7: 14 | N7: 2 | O7: 23
A8: 2.55 | B8: 147 | L8: 2.45 | M8: 7 | N8: 2.2 | O8: 14
A9: 3 | B9: 1662 | L9: 2.5 | M9: 106 | N9: 2.45 | O9: 7
A10: 3.1 | B10: 296 | L10: 2.55 | M10: 12 | N10: 2.5 | O10: 106
A11: 3.25 | B11: 451 | L11: 3 | M11: 132 | N11: 2.55 | O11: 12
A12: 3.5 | B12: 810 | L12: 3.1 | M12: 23 | N12: 3 | O12: 132
A13: 3.75 | B13: 1155 | L13: 3.25 | M13: 35 | N13: 3.1 | O13: 23
A14: 4 | B14: 492 | L14: 3.5 | M14: 62 | N14: 3.25 | O14: 35
A15: 4.25 | B15: 247 | L15: 3.75 | M15: 86 | N15: 3.5 | O15: 62
A16: 4.4 | B16: 374 | L16: 4 | M16: 38 | N16: 3.75 | O16: 86
A17: 4.5 | B17: 319 | L17: 4.25 | M17: 18 | N17: 4 | O17: 38
A18: 4.75 | B18: 171 | L18: 4.4 | M18: 30 | N18: 4.25 | O18: 18
... A30: Grand Total | B30: 13141 | L30: 9 | M30: 6 | N30: 8.5 | O30: 20
L31: 9.5 | M31: 7 | N31: 9 | O31: 6
L32: Grand Total | M32: 1000 | N32: 9.5 | O32: 7
N33: Grand Total | O33: 1000

Sheet Revenue Overview (2)
K15: Revenue Performance Overview
L37: Sales Performance by Time
L60: Sales trends across products and time intervals
N85: Recommendations and Insights

Sheet Revenue Overview
K15: Revenue Performance Overview
L37: Sales Performance by Time
L60: Sales trends across products and time intervals
N85: Recommendations and Insights

Sheet Bright Coffee Shop dataset
A1: transaction_id | B1: transaction_date | C1: year | D1: month | E1: month_name | F1: day | G1: day_name | H1: transaction_time | I1: hour | J1: time_of_day | K1: transaction_qty | L1: store_id | M1: store_location | N1: product_id | O1: product_category | P1: product_type | Q1: product_detail | R1: unit_price | S1: revenue | T1: Day_classification
A2: 1 | B2: 44927 | C2: 2023 | D2: 1 | E2: Jan | F2: 1 | G2: Sun | H2: 46203.379 | I2: 7 | J2: Morning | K2: 2 | L2: 5 | M2: Lower Manhattan | N2: 32 | O2: Coffee | P2: Gourmet brewed coffee | Q2: Ethiopia Rg | R2: 3 | S2: 6 | T2: Weekend
A3: 2 | B3: 44927 | C3: 2023 | D3: 1 | E3: Jan | F3: 1 | G3: Sun | H3: 46203.381 | I3: 7 | J3: Morning | K3: 2 | L3: 5 | M3: Lower Manhattan | N3: 57 | O3: Tea | P3: Brewed Chai tea | Q3: Spicy Eye Opener Chai Lg | R3: 3.1 | S3: 6.2 | T3: Weekend
A4: 3 | B4: 44927 | C4: 2023 | D4: 1 | E4: Jan | F4: 1 | G4: Sun | H4: 46203.385 | I4: 7 | J4: Morning | K4: 2 | L4: 5 | M4: Lower Manhattan | N4: 59 | O4: Drinking Chocolate | P4: Hot chocolate | Q4: Dark chocolate Lg | R4: 4.5 | S4: 9 | T4: Weekend
A5: 4 | B5: 44927 | C5: 2023 | D5: 1 | E5: Jan | F5: 1 | G5: Sun | H5: 46203.389 | I5: 7 | J5: Morning | K5: 1 | L5: 5 | M5: Lower Manhattan | N5: 22 | O5: Coffee | P5: Drip coffee | Q5: Our Old Time Diner Blend Sm | R5: 2 | S5: 2 | T5: Weekend
A6: 5 | B6: 44927 | C6: 2023 | D6: 1 | E6: Jan | F6: 1 | G6: Sun | H6: 46203.391 | I6: 7 | J6: Morning | K6: 2 | L6: 5 | M6: Lower Manhattan | N6: 57 | O6: Tea | P6: Brewed Chai tea | Q6: Spicy Eye Opener Chai Lg | R6: 3.1 | S6: 6.2 | T6: Weekend
A7: 6 | B7: 44927 | C7: 2023 | D7: 1 | E7: Jan | F7: 1 | G7: Sun | H7: 46203.391 | I7: 7 | J7: Morning | K7: 1 | L7: 5 | M7: Lower Manhattan | N7: 77 | O7: Bakery | P7: Scone | Q7: Oatmeal Scone | R7: 3 | S7: 3 | T7: Weekend
A8: 7 | B8: 44927 | C8: 2023 | D8: 1 | E8: Jan | F8: 1 | G8: Sun | H8: 46203.393 | I8: 7 | J8: Morning | K8: 1 | L8: 5 | M8: Lower Manhattan | N8: 22 | O8: Coffee | P8: Drip coffee | Q8: Our Old Time Diner Blend Sm | R8: 2 | S8: 2 | T8: Weekend
A9: 8 | B9: 44927 | C9: 2023 | D9: 1 | E9: Jan | F9: 1 | G9: Sun | H9: 46203.398 | I9: 7 | J9: Morning | K9: 2 | L9: 5 | M9: Lower Manhattan | N9: 28 | O9: Coffee | P9: Gourmet brewed coffee | Q9: Columbian Medium Roast Sm | R9: 2 | S9: 4 | T9: Weekend
A10: 9 | B10: 44927 | C10: 2023 | D10: 1 | E10: Jan | F10: 1 | G10: Sun | H10: 46203.402 | I10: 7 | J10: Morning | K10: 1 | L10: 5 | M10: Lower Manhattan | N10: 39 | O10: Coffee | P10: Barista Espresso | Q10: Latte Rg | R10: 4.25 | S10: 4.25 | T10: Weekend
A11: 10 | B11: 44927 | C11: 2023 | D11: 1 | E11: Jan | F11: 1 | G11: Sun | H11: 46203.402 | I11: 7 | J11: Morning | K11: 2 | L11: 5 | M11: Lower Manhattan | N11: 58 | O11: Drinking Chocolate | P11: Hot chocolate | Q11: Dark chocolate Rg | R11: 3.5 | S11: 7 | T11: Weekend
A12: 11 | B12: 44927 | C12: 2023 | D12: 1 | E12: Jan | F12: 1 | G12: Sun | H12: 46203.405 | I12: 7 | J12: Morning | K12: 1 | L12: 5 | M12: Lower Manhattan | N12: 56 | O12: Tea | P12: Brewed Chai tea | Q12: Spicy Eye Opener Chai Rg | R12: 2.55 | S12: 2.55 | T12: Weekend
A13: 12 | B13: 44927 | C13: 2023 | D13: 1 | E13: Jan | F13: 1 | G13: Sun | H13: 46203.406 | I13: 7 | J13: Morning | K13: 2 | L13: 5 | M13: Lower Manhattan | N13: 33 | O13: Coffee | P13: Gourmet brewed coffee | Q13: Ethiopia Lg | R13: 3.5 | S13: 7 | T13: Weekend
... A1001: 1000 | B1001: 44928 | C1001: 2023 | D1001: 1 | E1001: Jan | F1001: 2 | G1001: Mon | H1001: 46203.805 | I1001: 17 | J1001: Evening | K1001: 1 | L1001: 8 | M1001: Hell's Kitchen | N1001: 54 | O1001: Tea | P1001: Brewed Chai tea | Q1001: Morning Sunrise Chai Rg | R1001: 2.5 | S1001: 2.5 | T1001: Weekday

Sheet  Dashboard

Sheet Product Insights
A1: Product Insights
A2: Which products generate the most revenue and where performance can be improved.
A4: CATEGORY PERFORMANCE | G4: TOP PRODUCT TYPES BY REVENUE
A5: Product Category | B5: Revenue | C5: Transactions | D5: Units | E5: Avg Ticket | G5: Product Type | H5: Revenue | I5: Transactions | J5: Units | K5: Avg Ticket
A6: =Analysis!A2 -> Coffee | B6: =Analysis!B2 -> 2037.5 | C6: =Analysis!C2 -> 444 | D6: =Analysis!D2 -> 675 | E6: =Analysis!E2 -> 4.588964 | G6: =Analysis!G2 -> Barista Espresso | H6: =Analysis!H2 -> 649.25 | I6: =Analysis!I2 -> 115 | J6: =Analysis!J2 -> 175 | K6: =Analysis!K2 -> 5.6456522
A7: =Analysis!A3 -> Tea | B7: =Analysis!B3 -> 1421.7 | C7: =Analysis!C3 -> 344 | D7: =Analysis!D3 -> 506 | E7: =Analysis!E3 -> 4.1328488 | G7: =Analysis!G3 -> Brewed Chai tea | H7: =Analysis!H3 -> 556.2 | I7: =Analysis!I3 -> 134 | J7: =Analysis!J3 -> 191 | K7: =Analysis!K3 -> 4.1507463
A8: =Analysis!A4 -> Bakery | B8: =Analysis!B4 -> 471 | C8: =Analysis!C4 -> 132 | D8: =Analysis!D4 -> 132 | E8: =Analysis!E4 -> 3.5681818 | G8: =Analysis!G4 -> Gourmet brewed coffee | H8: =Analysis!H4 -> 487.7 | I8: =Analysis!I4 -> 116 | J8: =Analysis!J4 -> 183 | K8: =Analysis!K4 -> 4.2043103
A9: =Analysis!A5 -> Drinking Chocolate | B9: =Analysis!B5 -> 466 | C9: =Analysis!C5 -> 80 | D9: =Analysis!D5 -> 114 | E9: =Analysis!E5 -> 5.825 | G9: =Analysis!G5 -> Hot chocolate | H9: =Analysis!H5 -> 466 | I9: =Analysis!I5 -> 80 | J9: =Analysis!J5 -> 114 | K9: =Analysis!K5 -> 5.825
G10: =Analysis!G6 -> Brewed herbal tea | H10: =Analysis!H6 -> 351.5 | I10: =Analysis!I6 -> 84 | J10: =Analysis!J6 -> 128 | K10: =Analysis!K6 -> 4.1845238
G11: =Analysis!G7 -> Organic brewed coffee | H11: =Analysis!H7 -> 335.6 | I11: =Analysis!I7 -> 74 | J11: =Analysis!J7 -> 117 | K11: =Analysis!K7 -> 4.5351351
G12: =Analysis!G8 -> Brewed Black tea | H12: =Analysis!H8 -> 318 | I12: =Analysis!I8 -> 78 | J12: =Analysis!J8 -> 116 | K12: =Analysis!K8 -> 4.0769231
G13: =Analysis!G9 -> Premium brewed coffee | H13: =Analysis!H9 -> 303.45 | I13: =Analysis!I9 -> 63 | J13: =Analysis!J9 -> 96 | K13: =Analysis!K9 -> 4.8166667
G14: =Analysis!G10 -> Drip coffee | H14: =Analysis!H10 -> 261.5 | I14: =Analysis!I10 -> 76 | J14: =Analysis!J10 -> 104 | K14: =Analysis!K10 -> 3.4407895
G15: =Analysis!G11 -> Scone | H15: =Analysis!H11 -> 228.25 | I15: =Analysis!I11 -> 63 | J15: =Analysis!J11 -> 63 | K15: =Analysis!K11 -> 3.6230159
A18: PRODUCT TAKEAWAYS
A19: The revenue mix is concentrated in Coffee, led by Barista Espresso. Use the top product types as anchor items for bundles, and test offers that attach Bakery or lower-volume drinks to peak coffee/tea orders.

Sheet Time Insights
A1: Time Insights
A2: Store performance by time of day, hour, date, and weekday/weekend classification.
A4: TIME OF DAY PERFORMANCE | G4: STORE PERFORMANCE
A5: Time of Day | B5: Revenue | C5: Transactions | D5: Units | E5: Avg Ticket | G5: Store Location | H5: Revenue | I5: Transactions | J5: Units | K5: Avg Ticket
A6: =Analysis!M2 -> Afternoon | B6: =Analysis!N2 -> 2328.25 | C6: =Analysis!O2 -> 537 | D6: =Analysis!P2 -> 770 | E6: =Analysis!Q2 -> 4.3356611 | G6: =Analysis!Y2 -> Hell's Kitchen | H6: =Analysis!Z2 -> 1506 | I6: =Analysis!AA2 -> 339 | J6: =Analysis!AB2 -> 485 | K6: =Analysis!AC2 -> 4.4424779
A7: =Analysis!M3 -> Morning | B7: =Analysis!N3 -> 1350.8 | C7: =Analysis!O3 -> 310 | D7: =Analysis!P3 -> 435 | E7: =Analysis!Q3 -> 4.3574194 | G7: =Analysis!Y3 -> Astoria | H7: =Analysis!Z3 -> 1502.55 | I7: =Analysis!AA3 -> 337 | J7: =Analysis!AB3 -> 484 | K7: =Analysis!AC3 -> 4.4586053
A8: =Analysis!M4 -> Evening | B8: =Analysis!N4 -> 717.15 | C8: =Analysis!O4 -> 153 | D8: =Analysis!P4 -> 222 | E8: =Analysis!Q4 -> 4.6872549 | G8: =Analysis!Y4 -> Lower Manhattan | H8: =Analysis!Z4 -> 1387.65 | I8: =Analysis!AA4 -> 324 | J8: =Analysis!AB4 -> 458 | K8: =Analysis!AC4 -> 4.2828704
A13: TIME TAKEAWAYS
A14: Afternoon is the strongest daypart, with hour 13:00 standing out as the highest-revenue hour. Use this period for staffing and premium add-on selling, while testing slower-hour offers that pull demand earlier or later in the day.

Sheet Recommendations
A1: -
A2: Prioritized actions to grow revenue and improve product performance.
A4: CEO ACTION PLAN
A5: Priority | B5: Recommendation | C5: Evidence from Data | D5: Expected Impact | E5: Owner Focus
A6: 1 | B6: Protect and promote Barista Espresso | C6: Barista Espresso is the highest-revenue product type in the sample. | D6: Increase revenue from proven demand. | E6: Marketing + Store Ops
A7: 2 | B7: Build bundles around Coffee | C7: Coffee is the top category by revenue, creating an anchor for add-on offers. | D7: Lift average ticket and cross-sell attach rate. | E7: Product + Merchandising
A8: 3 | B8: Optimize staffing for Afternoon | C8: Afternoon is the strongest time of day and hour 13:00 is the peak hour. | D8: Improve service speed and capture peak demand. | E8: Store Ops
A9: 4 | B9: Revive slower dayparts with targeted offers | C9: Revenue is uneven across time intervals in the hourly/daypart view. | D9: Fill demand gaps without discounting peak periods. | E9: Marketing
A10: 5 | B10: Replicate practices from Hell's Kitchen | C10: Hell's Kitchen leads store revenue among locations in the dataset. | D10: Spread successful local execution across stores. | E10: Regional Ops
A12: HOW TO USE THIS WORKBOOK
A13: Update or append rows in the Bright Coffee Shop dataset table; all KPI cards, formulas, and chart source tables recalculate from structured table references. Review CEO Dashboard first for the executive view, then use Product Insights and Time Insights for supporting detail.
A18: DETAILED SALES PERFORMANCE IMPROVEMENT PLAN
A19: Focus Area | B19: Recommendation | C19: Data Signal | D19: How to Execute | E19: KPI to Track | F19: Priority
A20: Product mix | B20: Lead campaigns with Barista Espresso and Coffee | C20: Barista Espresso is the top product type; Coffee is the top category. | D20: Feature Barista Espresso in menu boards, staff scripts, and digital promos; pair Coffee with Bakery add-ons. | E20: Revenue by product type; attach rate | F20: High
A21: Bundling | B21: Create Coffee + Bakery bundles | C21: Bakery revenue is much smaller than Coffee, creating cross-sell upside. | D21: Offer small pastry add-ons during Coffee purchases and test bundle pricing during peak traffic. | E21: Average ticket; Bakery units | F21: High
A22: Daypart execution | B22: Staff and stock for Afternoon peak | C22: Afternoon generates the highest revenue. | D22: Schedule stronger coverage before peak; pre-stock fast-moving products; reduce queue friction. | E22: Afternoon revenue; transactions/hour | F22: High
A23: Slow-period growth | B23: Lift Evening demand | C23: Evening is the lowest daypart by revenue. | D23: Run limited evening offers, loyalty rewards, or “second drink” promotions after peak hours. | E23: Evening revenue; evening transaction count | F23: Medium
A24: Store operations | B24: Replicate Hell's Kitchen performance | C24: Hell's Kitchen leads store revenue. | D24: Review staffing, merchandising, and service practices at Hell's Kitchen and copy what works to other stores. | E24: Revenue by store; avg ticket by store | F24: Medium
A25: Pricing and margin | B25: Protect high average-ticket products | C25: Drinking Chocolate has a high average ticket despite lower volume. | D25: Promote selectively rather than discount heavily; use as a premium upsell. | E25: Avg ticket; units sold | F25: Medium
A26: Product assortment | B26: Review low-revenue product types | C26: Lowest ranked items contribute less revenue than core beverages. | D26: Keep only profitable SKUs, rotate low sellers, and test seasonal alternatives. | E26: Revenue per SKU; inventory waste | F26: Medium
A27: Campaign measurement | B27: Track before/after campaign lifts | C27: All dashboards are formula-driven from the source table. | D27: Compare revenue, units, and ticket size before and after each promotion window. | E27: Revenue lift; unit lift; avg ticket lift | F27: High
A30: EXECUTIVE SUMMARY
A31: The strongest near-term path is to protect the revenue core: Coffee and Barista Espresso. Pair that with operational focus on the Afternoon peak, where demand is already strongest, then use targeted bundles and promotions to lift Bakery attachment and Evening demand. Store-level playbooks from Hell's Kitchen should be reviewed and copied across other locations to improve consistency.

Sheet Analysis
A1: Product Category | B1: Revenue | C1: Transactions | D1: Units | E1: Avg Ticket | G1: Product Type | H1: Revenue | I1: Transactions | J1: Units | K1: Avg Ticket | M1: Time of Day | N1: Revenue | O1: Transactions | P1: Units | Q1: Avg Ticket | S1: Hour | T1: Revenue | U1: Transactions | V1: Units | W1: Avg Ticket | Y1: Store Location | Z1: Revenue | AA1: Transactions | AB1: Units | AC1: Avg Ticket | AE1: Day | AF1: Revenue | AG1: Transactions | AH1: Units | AI1: Avg Ticket | AK1: Day Class | AL1: Revenue | AM1: Transactions | AN1: Units | AO1: Avg Ticket | AQ1: Product Category | AR1: Morning | AS1: Afternoon | AT1: Evening | AU1: Total
A2: Coffee | B2: =SUMIFS(Bright_Coffee_Shop_dataset[revenue],Bright_Coffee_Shop_dataset[product_category],A2) -> 2037.5 | C2: =COUNTIFS(Bright_Coffee_Shop_dataset[product_category],A2) -> 444 | D2: =SUMIFS(Bright_Coffee_Shop_dataset[transaction_qty],Bright_Coffee_Shop_dataset[product_category],A2) -> 675 | E2: =IFERROR(B2/C2,0) -> 4.588964 | G2: Barista Espresso | H2: =SUMIFS(Bright_Coffee_Shop_dataset[revenue],Bright_Coffee_Shop_dataset[product_type],G2) -> 649.25 | I2: =COUNTIFS(Bright_Coffee_Shop_dataset[product_type],G2) -> 115 | J2: =SUMIFS(Bright_Coffee_Shop_dataset[transaction_qty],Bright_Coffee_Shop_dataset[product_type],G2) -> 175 | K2: =IFERROR(H2/I2,0) -> 5.6456522 | M2: Afternoon | N2: =SUMIFS(Bright_Coffee_Shop_dataset[revenue],Bright_Coffee_Shop_dataset[time_of_day],M2) -> 2328.25 | O2: =COUNTIFS(Bright_Coffee_Shop_dataset[time_of_day],M2) -> 537 | P2: =SUMIFS(Bright_Coffee_Shop_dataset[transaction_qty],Bright_Coffee_Shop_dataset[time_of_day],M2) -> 770 | Q2: =IFERROR(N2/O2,0) -> 4.3356611 | S2: 7 | T2: =SUMIFS(Bright_Coffee_Shop_dataset[revenue],Bright_Coffee_Shop_dataset[hour],S2) -> 136.15 | U2: =COUNTIFS(Bright_Coffee_Shop_dataset[hour],S2) -> 31 | V2: =SUMIFS(Bright_Coffee_Shop_dataset[transaction_qty],Bright_Coffee_Shop_dataset[hour],S2) -> 43 | W2: =IFERROR(T2/U2,0) -> 4.3919355 | Y2: Hell's Kitchen | Z2: =SUMIFS(Bright_Coffee_Shop_dataset[revenue],Bright_Coffee_Shop_dataset[store_location],Y2) -> 1506 | AA2: =COUNTIFS(Bright_Coffee_Shop_dataset[store_location],Y2) -> 339 | AB2: =SUMIFS(Bright_Coffee_Shop_dataset[transaction_qty],Bright_Coffee_Shop_dataset[store_location],Y2) -> 485 | AC2: =IFERROR(Z2/AA2,0) -> 4.4424779 | AE2: 1 | AF2: =SUMIFS(Bright_Coffee_Shop_dataset[revenue],Bright_Coffee_Shop_dataset[day],AE2) -> 2508.2 | AG2: =COUNTIFS(Bright_Coffee_Shop_dataset[day],AE2) -> 550 | AH2: =SUMIFS(Bright_Coffee_Shop_dataset[transaction_qty],Bright_Coffee_Shop_dataset[day],AE2) -> 802 | AI2: =IFERROR(AF2/AG2,0) -> 4.5603636 | AK2: Weekday | AL2: =SUMIFS(Bright_Coffee_Shop_dataset[revenue],Bright_Coffee_Shop_dataset[Day_classification],AK2) -> 1888 | AM2: =COUNTIFS(Bright_Coffee_Shop_dataset[Day_classification],AK2) -> 450 | AN2: =SUMIFS(Bright_Coffee_Shop_dataset[transaction_qty],Bright_Coffee_Shop_dataset[Day_classification],AK2) -> 625 | AO2: =IFERROR(AL2/AM2,0) -> 4.1955556 | AQ2: Coffee | AR2: =SUMIFS(Bright_Coffee_Shop_dataset[revenue],Bright_Coffee_Shop_dataset[product_category],AQ2,Bright_Coffee_Shop_dataset[time_of_day],AR$1) -> 610.2 | AS2: =SUMIFS(Bright_Coffee_Shop_dataset[revenue],Bright_Coffee_Shop_dataset[product_category],AQ2,Bright_Coffee_Shop_dataset[time_of_day],AS$1) -> 1118.85 | AT2: =SUMIFS(Bright_Coffee_Shop_dataset[revenue],Bright_Coffee_Shop_dataset[product_category],AQ2,Bright_Coffee_Shop_dataset[time_of_day],AT$1) -> 308.45 | AU2: =SUM(AR2:AT2) -> 2037.5
A3: Tea | B3: =SUMIFS(Bright_Coffee_Shop_dataset[revenue],Bright_Coffee_Shop_dataset[product_category],A3) -> 1421.7 | C3: =COUNTIFS(Bright_Coffee_Shop_dataset[product_category],A3) -> 344 | D3: =SUMIFS(Bright_Coffee_Shop_dataset[transaction_qty],Bright_Coffee_Shop_dataset[product_category],A3) -> 506 | E3: =IFERROR(B3/C3,0) -> 4.1328488 | G3: Brewed Chai tea | H3: =SUMIFS(Bright_Coffee_Shop_dataset[revenue],Bright_Coffee_Shop_dataset[product_type],G3) -> 556.2 | I3: =COUNTIFS(Bright_Coffee_Shop_dataset[product_type],G3) -> 134 | J3: =SUMIFS(Bright_Coffee_Shop_dataset[transaction_qty],Bright_Coffee_Shop_dataset[product_type],G3) -> 191 | K3: =IFERROR(H3/I3,0) -> 4.1507463 | M3: Morning | N3: =SUMIFS(Bright_Coffee_Shop_dataset[revenue],Bright_Coffee_Shop_dataset[time_of_day],M3) -> 1350.8 | O3: =COUNTIFS(Bright_Coffee_Shop_dataset[time_of_day],M3) -> 310 | P3: =SUMIFS(Bright_Coffee_Shop_dataset[transaction_qty],Bright_Coffee_Shop_dataset[time_of_day],M3) -> 435 | Q3: =IFERROR(N3/O3,0) -> 4.3574194 | S3: 8 | T3: =SUMIFS(Bright_Coffee_Shop_dataset[revenue],Bright_Coffee_Shop_dataset[hour],S3) -> 192.85 | U3: =COUNTIFS(Bright_Coffee_Shop_dataset[hour],S3) -> 45 | V3: =SUMIFS(Bright_Coffee_Shop_dataset[transaction_qty],Bright_Coffee_Shop_dataset[hour],S3) -> 62 | W3: =IFERROR(T3/U3,0) -> 4.2855556 | Y3: Astoria | Z3: =SUMIFS(Bright_Coffee_Shop_dataset[revenue],Bright_Coffee_Shop_dataset[store_location],Y3) -> 1502.55 | AA3: =COUNTIFS(Bright_Coffee_Shop_dataset[store_location],Y3) -> 337 | AB3: =SUMIFS(Bright_Coffee_Shop_dataset[transaction_qty],Bright_Coffee_Shop_dataset[store_location],Y3) -> 484 | AC3: =IFERROR(Z3/AA3,0) -> 4.4586053 | AE3: 2 | AF3: =SUMIFS(Bright_Coffee_Shop_dataset[revenue],Bright_Coffee_Shop_dataset[day],AE3) -> 1888 | AG3: =COUNTIFS(Bright_Coffee_Shop_dataset[day],AE3) -> 450 | AH3: =SUMIFS(Bright_Coffee_Shop_dataset[transaction_qty],Bright_Coffee_Shop_dataset[day],AE3) -> 625 | AI3: =IFERROR(AF3/AG3,0) -> 4.1955556 | AK3: Weekend | AL3: =SUMIFS(Bright_Coffee_Shop_dataset[revenue],Bright_Coffee_Shop_dataset[Day_classification],AK3) -> 2508.2 | AM3: =COUNTIFS(Bright_Coffee_Shop_dataset[Day_classification],AK3) -> 550 | AN3: =SUMIFS(Bright_Coffee_Shop_dataset[transaction_qty],Bright_Coffee_Shop_dataset[Day_classification],AK3) -> 802 | AO3: =IFERROR(AL3/AM3,0) -> 4.5603636 | AQ3: Tea | AR3: =SUMIFS(Bright_Coffee_Shop_dataset[revenue],Bright_Coffee_Shop_dataset[product_category],AQ3,Bright_Coffee_Shop_dataset[time_of_day],AR$1) -> 408.35 | AS3: =SUMIFS(Bright_Coffee_Shop_dataset[revenue],Bright_Coffee_Shop_dataset[product_category],AQ3,Bright_Coffee_Shop_dataset[time_of_day],AS$1) -> 766.65 | AT3: =SUMIFS(Bright_Coffee_Shop_dataset[revenue],Bright_Coffee_Shop_dataset[product_category],AQ3,Bright_Coffee_Shop_dataset[time_of_day],AT$1) -> 246.7 | AU3: =SUM(AR3:AT3) -> 1421.7
A4: Bakery | B4: =SUMIFS(Bright_Coffee_Shop_dataset[revenue],Bright_Coffee_Shop_dataset[product_category],A4) -> 471 | C4: =COUNTIFS(Bright_Coffee_Shop_dataset[product_category],A4) -> 132 | D4: =SUMIFS(Bright_Coffee_Shop_dataset[transaction_qty],Bright_Coffee_Shop_dataset[product_category],A4) -> 132 | E4: =IFERROR(B4/C4,0) -> 3.5681818 | G4: Gourmet brewed coffee | H4: =SUMIFS(Bright_Coffee_Shop_dataset[revenue],Bright_Coffee_Shop_dataset[product_type],G4) -> 487.7 | I4: =COUNTIFS(Bright_Coffee_Shop_dataset[product_type],G4) -> 116 | J4: =SUMIFS(Bright_Coffee_Shop_dataset[transaction_qty],Bright_Coffee_Shop_dataset[product_type],G4) -> 183 | K4: =IFERROR(H4/I4,0) -> 4.2043103 | M4: Evening | N4: =SUMIFS(Bright_Coffee_Shop_dataset[revenue],Bright_Coffee_Shop_dataset[time_of_day],M4) -> 717.15 | O4: =COUNTIFS(Bright_Coffee_Shop_dataset[time_of_day],M4) -> 153 | P4: =SUMIFS(Bright_Coffee_Shop_dataset[transaction_qty],Bright_Coffee_Shop_dataset[time_of_day],M4) -> 222 | Q4: =IFERROR(N4/O4,0) -> 4.6872549 | S4: 9 | T4: =SUMIFS(Bright_Coffee_Shop_dataset[revenue],Bright_Coffee_Shop_dataset[hour],S4) -> 324.6 | U4: =COUNTIFS(Bright_Coffee_Shop_dataset[hour],S4) -> 76 | V4: =SUMIFS(Bright_Coffee_Shop_dataset[transaction_qty],Bright_Coffee_Shop_dataset[hour],S4) -> 104 | W4: =IFERROR(T4/U4,0) -> 4.2710526 | Y4: Lower Manhattan | Z4: =SUMIFS(Bright_Coffee_Shop_dataset[revenue],Bright_Coffee_Shop_dataset[store_location],Y4) -> 1387.65 | AA4: =COUNTIFS(Bright_Coffee_Shop_dataset[store_location],Y4) -> 324 | AB4: =SUMIFS(Bright_Coffee_Shop_dataset[transaction_qty],Bright_Coffee_Shop_dataset[store_location],Y4) -> 458 | AC4: =IFERROR(Z4/AA4,0) -> 4.2828704 | AQ4: Bakery | AR4: =SUMIFS(Bright_Coffee_Shop_dataset[revenue],Bright_Coffee_Shop_dataset[product_category],AQ4,Bright_Coffee_Shop_dataset[time_of_day],AR$1) -> 158.5 | AS4: =SUMIFS(Bright_Coffee_Shop_dataset[revenue],Bright_Coffee_Shop_dataset[product_category],AQ4,Bright_Coffee_Shop_dataset[time_of_day],AS$1) -> 245.25 | AT4: =SUMIFS(Bright_Coffee_Shop_dataset[revenue],Bright_Coffee_Shop_dataset[product_category],AQ4,Bright_Coffee_Shop_dataset[time_of_day],AT$1) -> 67.25 | AU4: =SUM(AR4:AT4) -> 471
A5: Drinking Chocolate | B5: =SUMIFS(Bright_Coffee_Shop_dataset[revenue],Bright_Coffee_Shop_dataset[product_category],A5) -> 466 | C5: =COUNTIFS(Bright_Coffee_Shop_dataset[product_category],A5) -> 80 | D5: =SUMIFS(Bright_Coffee_Shop_dataset[transaction_qty],Bright_Coffee_Shop_dataset[product_category],A5) -> 114 | E5: =IFERROR(B5/C5,0) -> 5.825 | G5: Hot chocolate | H5: =SUMIFS(Bright_Coffee_Shop_dataset[revenue],Bright_Coffee_Shop_dataset[product_type],G5) -> 466 | I5: =COUNTIFS(Bright_Coffee_Shop_dataset[product_type],G5) -> 80 | J5: =SUMIFS(Bright_Coffee_Shop_dataset[transaction_qty],Bright_Coffee_Shop_dataset[product_type],G5) -> 114 | K5: =IFERROR(H5/I5,0) -> 5.825 | S5: 10 | T5: =SUMIFS(Bright_Coffee_Shop_dataset[revenue],Bright_Coffee_Shop_dataset[hour],S5) -> 222.9 | U5: =COUNTIFS(Bright_Coffee_Shop_dataset[hour],S5) -> 52 | V5: =SUMIFS(Bright_Coffee_Shop_dataset[transaction_qty],Bright_Coffee_Shop_dataset[hour],S5) -> 71 | W5: =IFERROR(T5/U5,0) -> 4.2865385 | AQ5: Drinking Chocolate | AR5: =SUMIFS(Bright_Coffee_Shop_dataset[revenue],Bright_Coffee_Shop_dataset[product_category],AQ5,Bright_Coffee_Shop_dataset[time_of_day],AR$1) -> 173.75 | AS5: =SUMIFS(Bright_Coffee_Shop_dataset[revenue],Bright_Coffee_Shop_dataset[product_category],AQ5,Bright_Coffee_Shop_dataset[time_of_day],AS$1) -> 197.5 | AT5: =SUMIFS(Bright_Coffee_Shop_dataset[revenue],Bright_Coffee_Shop_dataset[product_category],AQ5,Bright_Coffee_Shop_dataset[time_of_day],AT$1) -> 94.75 | AU5: =SUM(AR5:AT5) -> 466
G6: Brewed herbal tea | H6: =SUMIFS(Bright_Coffee_Shop_dataset[revenue],Bright_Coffee_Shop_dataset[product_type],G6) -> 351.5 | I6: =COUNTIFS(Bright_Coffee_Shop_dataset[product_type],G6) -> 84 | J6: =SUMIFS(Bright_Coffee_Shop_dataset[transaction_qty],Bright_Coffee_Shop_dataset[product_type],G6) -> 128 | K6: =IFERROR(H6/I6,0) -> 4.1845238 | S6: 11 | T6: =SUMIFS(Bright_Coffee_Shop_dataset[revenue],Bright_Coffee_Shop_dataset[hour],S6) -> 474.3 | U6: =COUNTIFS(Bright_Coffee_Shop_dataset[hour],S6) -> 106 | V6: =SUMIFS(Bright_Coffee_Shop_dataset[transaction_qty],Bright_Coffee_Shop_dataset[hour],S6) -> 155 | W6: =IFERROR(T6/U6,0) -> 4.4745283
G7: Organic brewed coffee | H7: =SUMIFS(Bright_Coffee_Shop_dataset[revenue],Bright_Coffee_Shop_dataset[product_type],G7) -> 335.6 | I7: =COUNTIFS(Bright_Coffee_Shop_dataset[product_type],G7) -> 74 | J7: =SUMIFS(Bright_Coffee_Shop_dataset[transaction_qty],Bright_Coffee_Shop_dataset[product_type],G7) -> 117 | K7: =IFERROR(H7/I7,0) -> 4.5351351 | S7: 12 | T7: =SUMIFS(Bright_Coffee_Shop_dataset[revenue],Bright_Coffee_Shop_dataset[hour],S7) -> 472.6 | U7: =COUNTIFS(Bright_Coffee_Shop_dataset[hour],S7) -> 116 | V7: =SUMIFS(Bright_Coffee_Shop_dataset[transaction_qty],Bright_Coffee_Shop_dataset[hour],S7) -> 159 | W7: =IFERROR(T7/U7,0) -> 4.0741379
G8: Brewed Black tea | H8: =SUMIFS(Bright_Coffee_Shop_dataset[revenue],Bright_Coffee_Shop_dataset[product_type],G8) -> 318 | I8: =COUNTIFS(Bright_Coffee_Shop_dataset[product_type],G8) -> 78 | J8: =SUMIFS(Bright_Coffee_Shop_dataset[transaction_qty],Bright_Coffee_Shop_dataset[product_type],G8) -> 116 | K8: =IFERROR(H8/I8,0) -> 4.0769231 | S8: 13 | T8: =SUMIFS(Bright_Coffee_Shop_dataset[revenue],Bright_Coffee_Shop_dataset[hour],S8) -> 530.45 | U8: =COUNTIFS(Bright_Coffee_Shop_dataset[hour],S8) -> 118 | V8: =SUMIFS(Bright_Coffee_Shop_dataset[transaction_qty],Bright_Coffee_Shop_dataset[hour],S8) -> 175 | W8: =IFERROR(T8/U8,0) -> 4.495339
G9: Premium brewed coffee | H9: =SUMIFS(Bright_Coffee_Shop_dataset[revenue],Bright_Coffee_Shop_dataset[product_type],G9) -> 303.45 | I9: =COUNTIFS(Bright_Coffee_Shop_dataset[product_type],G9) -> 63 | J9: =SUMIFS(Bright_Coffee_Shop_dataset[transaction_qty],Bright_Coffee_Shop_dataset[product_type],G9) -> 96 | K9: =IFERROR(H9/I9,0) -> 4.8166667 | S9: 14 | T9: =SUMIFS(Bright_Coffee_Shop_dataset[revenue],Bright_Coffee_Shop_dataset[hour],S9) -> 457.35 | U9: =COUNTIFS(Bright_Coffee_Shop_dataset[hour],S9) -> 98 | V9: =SUMIFS(Bright_Coffee_Shop_dataset[transaction_qty],Bright_Coffee_Shop_dataset[hour],S9) -> 145 | W9: =IFERROR(T9/U9,0) -> 4.6668367
G10: Drip coffee | H10: =SUMIFS(Bright_Coffee_Shop_dataset[revenue],Bright_Coffee_Shop_dataset[product_type],G10) -> 261.5 | I10: =COUNTIFS(Bright_Coffee_Shop_dataset[product_type],G10) -> 76 | J10: =SUMIFS(Bright_Coffee_Shop_dataset[transaction_qty],Bright_Coffee_Shop_dataset[product_type],G10) -> 104 | K10: =IFERROR(H10/I10,0) -> 3.4407895 | S10: 15 | T10: =SUMIFS(Bright_Coffee_Shop_dataset[revenue],Bright_Coffee_Shop_dataset[hour],S10) -> 466.5 | U10: =COUNTIFS(Bright_Coffee_Shop_dataset[hour],S10) -> 105 | V10: =SUMIFS(Bright_Coffee_Shop_dataset[transaction_qty],Bright_Coffee_Shop_dataset[hour],S10) -> 154 | W10: =IFERROR(T10/U10,0) -> 4.4428571
G11: Scone | H11: =SUMIFS(Bright_Coffee_Shop_dataset[revenue],Bright_Coffee_Shop_dataset[product_type],G11) -> 228.25 | I11: =COUNTIFS(Bright_Coffee_Shop_dataset[product_type],G11) -> 63 | J11: =SUMIFS(Bright_Coffee_Shop_dataset[transaction_qty],Bright_Coffee_Shop_dataset[product_type],G11) -> 63 | K11: =IFERROR(H11/I11,0) -> 3.6230159 | S11: 16 | T11: =SUMIFS(Bright_Coffee_Shop_dataset[revenue],Bright_Coffee_Shop_dataset[hour],S11) -> 401.35 | U11: =COUNTIFS(Bright_Coffee_Shop_dataset[hour],S11) -> 100 | V11: =SUMIFS(Bright_Coffee_Shop_dataset[transaction_qty],Bright_Coffee_Shop_dataset[hour],S11) -> 137 | W11: =IFERROR(T11/U11,0) -> 4.0135
G12: Brewed Green tea | H12: =SUMIFS(Bright_Coffee_Shop_dataset[revenue],Bright_Coffee_Shop_dataset[product_type],G12) -> 196 | I12: =COUNTIFS(Bright_Coffee_Shop_dataset[product_type],G12) -> 48 | J12: =SUMIFS(Bright_Coffee_Shop_dataset[transaction_qty],Bright_Coffee_Shop_dataset[product_type],G12) -> 71 | K12: =IFERROR(H12/I12,0) -> 4.0833333 | S12: 17 | T12: =SUMIFS(Bright_Coffee_Shop_dataset[revenue],Bright_Coffee_Shop_dataset[hour],S12) -> 316.15 | U12: =COUNTIFS(Bright_Coffee_Shop_dataset[hour],S12) -> 69 | V12: =SUMIFS(Bright_Coffee_Shop_dataset[transaction_qty],Bright_Coffee_Shop_dataset[hour],S12) -> 99 | W12: =IFERROR(T12/U12,0) -> 4.5818841
G13: Pastry | H13: =SUMIFS(Bright_Coffee_Shop_dataset[revenue],Bright_Coffee_Shop_dataset[product_type],G13) -> 134 | I13: =COUNTIFS(Bright_Coffee_Shop_dataset[product_type],G13) -> 37 | J13: =SUMIFS(Bright_Coffee_Shop_dataset[transaction_qty],Bright_Coffee_Shop_dataset[product_type],G13) -> 37 | K13: =IFERROR(H13/I13,0) -> 3.6216216 | S13: 18 | T13: =SUMIFS(Bright_Coffee_Shop_dataset[revenue],Bright_Coffee_Shop_dataset[hour],S13) -> 231.4 | U13: =COUNTIFS(Bright_Coffee_Shop_dataset[hour],S13) -> 48 | V13: =SUMIFS(Bright_Coffee_Shop_dataset[transaction_qty],Bright_Coffee_Shop_dataset[hour],S13) -> 74 | W13: =IFERROR(T13/U13,0) -> 4.8208333
G14: Biscotti | H14: =SUMIFS(Bright_Coffee_Shop_dataset[revenue],Bright_Coffee_Shop_dataset[product_type],G14) -> 108.75 | I14: =COUNTIFS(Bright_Coffee_Shop_dataset[product_type],G14) -> 32 | J14: =SUMIFS(Bright_Coffee_Shop_dataset[transaction_qty],Bright_Coffee_Shop_dataset[product_type],G14) -> 32 | K14: =IFERROR(H14/I14,0) -> 3.3984375 | S14: 19 | T14: =SUMIFS(Bright_Coffee_Shop_dataset[revenue],Bright_Coffee_Shop_dataset[hour],S14) -> 169.6 | U14: =COUNTIFS(Bright_Coffee_Shop_dataset[hour],S14) -> 36 | V14: =SUMIFS(Bright_Coffee_Shop_dataset[transaction_qty],Bright_Coffee_Shop_dataset[hour],S14) -> 49 | W14: =IFERROR(T14/U14,0) -> 4.7111111

Sheet Products Dashboard
A1: Products Dashboard
A2: Objective: identify which products generate the most revenue.
A4: TOP PRODUCT TYPES | G4: CATEGORY SUMMARY
A5: Product Type | B5: Revenue | C5: Transactions | D5: Units | E5: Avg Ticket | G5: Category | H5: Revenue | I5: Transactions | J5: Units | K5: Avg Ticket
A6: =Analysis!G2 -> Barista Espresso | B6: =Analysis!H2 -> 649.25 | C6: =Analysis!I2 -> 115 | D6: =Analysis!J2 -> 175 | E6: =Analysis!K2 -> 5.6456522 | G6: =Analysis!A2 -> Coffee | H6: =Analysis!B2 -> 2037.5 | I6: =Analysis!C2 -> 444 | J6: =Analysis!D2 -> 675 | K6: =Analysis!E2 -> 4.588964
A7: =Analysis!G3 -> Brewed Chai tea | B7: =Analysis!H3 -> 556.2 | C7: =Analysis!I3 -> 134 | D7: =Analysis!J3 -> 191 | E7: =Analysis!K3 -> 4.1507463 | G7: =Analysis!A3 -> Tea | H7: =Analysis!B3 -> 1421.7 | I7: =Analysis!C3 -> 344 | J7: =Analysis!D3 -> 506 | K7: =Analysis!E3 -> 4.1328488
A8: =Analysis!G4 -> Gourmet brewed coffee | B8: =Analysis!H4 -> 487.7 | C8: =Analysis!I4 -> 116 | D8: =Analysis!J4 -> 183 | E8: =Analysis!K4 -> 4.2043103 | G8: =Analysis!A4 -> Bakery | H8: =Analysis!B4 -> 471 | I8: =Analysis!C4 -> 132 | J8: =Analysis!D4 -> 132 | K8: =Analysis!E4 -> 3.5681818
A9: =Analysis!G5 -> Hot chocolate | B9: =Analysis!H5 -> 466 | C9: =Analysis!I5 -> 80 | D9: =Analysis!J5 -> 114 | E9: =Analysis!K5 -> 5.825 | G9: =Analysis!A5 -> Drinking Chocolate | H9: =Analysis!B5 -> 466 | I9: =Analysis!C5 -> 80 | J9: =Analysis!D5 -> 114 | K9: =Analysis!E5 -> 5.825
A10: =Analysis!G6 -> Brewed herbal tea | B10: =Analysis!H6 -> 351.5 | C10: =Analysis!I6 -> 84 | D10: =Analysis!J6 -> 128 | E10: =Analysis!K6 -> 4.1845238
A11: =Analysis!G7 -> Organic brewed coffee | B11: =Analysis!H7 -> 335.6 | C11: =Analysis!I7 -> 74 | D11: =Analysis!J7 -> 117 | E11: =Analysis!K7 -> 4.5351351 | G11: ="Finding: "&INDEX(Analysis!G2:G11,MATCH(MAX(Analysis!H2:H11),Analysis!H2:H11,0))&" is the top product type, while "&INDEX(Analysis!A2:A5,MATCH(MAX(Analysis!B2:B5),Analysis!B2:B5,0))&" is the strongest category. Prioritize these as anchor offers for campaigns and bundles." -> Finding: Barista Espresso is the top product type, while Coffee is the strongest category. Prioritize these as anchor offers for campaigns and bundles.
A12: =Analysis!G8 -> Brewed Black tea | B12: =Analysis!H8 -> 318 | C12: =Analysis!I8 -> 78 | D12: =Analysis!J8 -> 116 | E12: =Analysis!K8 -> 4.0769231
A13: =Analysis!G9 -> Premium brewed coffee | B13: =Analysis!H9 -> 303.45 | C13: =Analysis!I9 -> 63 | D13: =Analysis!J9 -> 96 | E13: =Analysis!K9 -> 4.8166667
A14: =Analysis!G10 -> Drip coffee | B14: =Analysis!H10 -> 261.5 | C14: =Analysis!I10 -> 76 | D14: =Analysis!J10 -> 104 | E14: =Analysis!K10 -> 3.4407895
A15: =Analysis!G11 -> Scone | B15: =Analysis!H11 -> 228.25 | C15: =Analysis!I11 -> 63 | D15: =Analysis!J11 -> 63 | E15: =Analysis!K11 -> 3.6230159

Sheet Daypart Dashboard
A1: Daypart Dashboard
A2: Objective: determine what time of day the store performs best.
A4: TIME OF DAY PERFORMANCE | G4: BEST INTERVAL
A5: Time of Day | B5: Revenue | C5: Transactions | D5: Units | E5: Avg Ticket | G5: ="Best time of day: "&INDEX(Analysis!M2:M4,MATCH(MAX(Analysis!N2:N4),Analysis!N2:N4,0))&" with "&TEXT(MAX(Analysis!N2:N4),"R#,##0.00")&" revenue. Peak hour: "&INDEX(Analysis!S2:S14,MATCH(MAX(Analysis!T2:T14),Analysis!T2:T14,0))&":00." -> Best time of day: Afternoon with R2328,250.00 revenue. Peak hour: 13:00.
A6: =Analysis!M2 -> Afternoon | B6: =Analysis!N2 -> 2328.25 | C6: =Analysis!O2 -> 537 | D6: =Analysis!P2 -> 770 | E6: =Analysis!Q2 -> 4.3356611
A7: =Analysis!M3 -> Morning | B7: =Analysis!N3 -> 1350.8 | C7: =Analysis!O3 -> 310 | D7: =Analysis!P3 -> 435 | E7: =Analysis!Q3 -> 4.3574194
A8: =Analysis!M4 -> Evening | B8: =Analysis!N4 -> 717.15 | C8: =Analysis!O4 -> 153 | D8: =Analysis!P4 -> 222 | E8: =Analysis!Q4 -> 4.6872549

Sheet Sales Trends Dashboard
A1: Sales Trends Dashboard
A2: Objective: show sales trends across products and time intervals.
A4: PRODUCT CATEGORY × TIME OF DAY REVENUE
A5: Product Category | B5: Morning | C5: Afternoon | D5: Evening | E5: Total | G5: ="Trend summary: Afternoon leads overall, and Coffee contributes the largest product revenue. Use the matrix to compare whether each product category is strongest in Morning, Afternoon, or Evening." -> Trend summary: Afternoon leads overall, and Coffee contributes the largest product revenue. Use the matrix to compare whether each product category is strongest in Morning, Afternoon, or Evening.
A6: =Analysis!AQ2 -> Coffee | B6: =Analysis!AR2 -> 610.2 | C6: =Analysis!AS2 -> 1118.85 | D6: =Analysis!AT2 -> 308.45 | E6: =Analysis!AU2 -> 2037.5
A7: =Analysis!AQ3 -> Tea | B7: =Analysis!AR3 -> 408.35 | C7: =Analysis!AS3 -> 766.65 | D7: =Analysis!AT3 -> 246.7 | E7: =Analysis!AU3 -> 1421.7
A8: =Analysis!AQ4 -> Bakery | B8: =Analysis!AR4 -> 158.5 | C8: =Analysis!AS4 -> 245.25 | D8: =Analysis!AT4 -> 67.25 | E8: =Analysis!AU4 -> 471
A9: =Analysis!AQ5 -> Drinking Chocolate | B9: =Analysis!AR5 -> 173.75 | C9: =Analysis!AS5 -> 197.5 | D9: =Analysis!AT5 -> 94.75 | E9: =Analysis!AU5 -> 466

Sheet Action Dashboard
A1: Action Dashboard
A2: Objective: recommendations for improving sales performance.
A4: PRIORITIZED ACTION PLAN
A5: Priority | B5: Recommendation | C5: Data Evidence | D5: Commercial Impact | E5: Owner
A6: 1 | B6: Promote top product type | C6: Barista Espresso is the highest-revenue product type. | D6: Protect and grow proven demand. | E6: Marketing + Store Ops
A7: 2 | B7: Bundle around Coffee | C7: Coffee contributes the largest category revenue. | D7: Increase average ticket through add-ons. | E7: Product + Merchandising
A8: 3 | B8: Staff for Afternoon peak | C8: Afternoon is the highest-revenue daypart. | D8: Improve speed and capture peak demand. | E8: Store Ops
A9: 4 | B9: Lift Evening demand | C9: Evening trails Morning and Afternoon revenue. | D9: Fill capacity with targeted offers. | E9: Marketing
A10: 5 | B10: Replicate top-store execution | C10: Hell's Kitchen leads store revenue. | D10: Spread successful practices to other stores. | E10: Regional Ops
A12: CEO MESSAGE
A13: Focus growth on the proven revenue core: Coffee and Barista Espresso. Protect service quality in the Afternoon peak, then use bundles and time-limited offers to pull incremental demand into weaker periods. Track the KPIs on the dashboard after each campaign to confirm revenue, transactions, units, and average ticket improve together.
A19: EXPANDED RECOMMENDATIONS
A20: Rank | B20: Action | C20: Why It Matters | D20: Execution Step | E20: Success Metric
A21: 1 | B21: Promote Barista Espresso + Coffee | C21: Top revenue product type and category. | D21: Make them campaign anchors and suggest as default upsell items. | E21: Product revenue
A22: 2 | B22: Bundle Coffee with Bakery | C22: Bakery has lower revenue but fits Coffee purchases. | D22: Test Coffee + pastry bundles during high traffic. | E22: Avg ticket / Bakery units
A23: 3 | B23: Optimize Afternoon operations | C23: Afternoon is the strongest daypart. | D23: Schedule more staff and pre-stock core products. | E23: Afternoon transactions/hour
A24: 4 | B24: Grow Evening sales | C24: Evening is the weakest interval. | D24: Use targeted evening offers and loyalty incentives. | E24: Evening revenue
A25: 5 | B25: Replicate Hell's Kitchen practices | C25: Top store performance indicates useful operating lessons. | D25: Copy merchandising and staffing practices to other stores. | E25: Revenue by store
A26: 6 | B26: Measure every campaign | C26: Dashboards recalculate from source data. | D26: Compare before/after revenue, units, and average ticket. | E26: Campaign lift
